fastbrick/__init__.py
fastbrick/cli.py
fastbrick-0.5.2.dist-info/LICENSE
fastbrick-0.5.2.dist-info/METADATA
fastbrick-0.5.2.dist-info/WHEEL
fastbrick-0.5.2.dist-info/entry_points.txt
fastbrick-0.5.2.dist-info/top_level.txt
fastbrick-0.5.2.dist-info/RECORD
