Metadata-Version: 2.1
Name: fastbrick
Version: 0.5.2
Summary: A CLI tool for generating FastAPI projects and apps
Home-page: UNKNOWN
Author: Sandeep Singh Negi
Author-email: sandeepnegi1710@gmail.com
License: UNKNOWN
Platform: UNKNOWN
Classifier: Programming Language :: Python :: 3
Classifier: License :: OSI Approved :: MIT License
Classifier: Operating System :: OS Independent
Requires-Python: >=3.7
Requires-Dist: fastapi
Requires-Dist: click
Requires-Dist: jinja2
